blacktex/__init__.py
blacktex/cli.py
blacktex/main.py
blacktex-0.9.0.dist-info/METADATA
blacktex-0.9.0.dist-info/WHEEL
blacktex-0.9.0.dist-info/entry_points.txt
blacktex-0.9.0.dist-info/top_level.txt
blacktex-0.9.0.dist-info/RECORD
