Metadata-Version: 2.4
Name: blacktex
Version: 0.9.0
Summary: Clean up your LaTeX files
Author-email: Nico Schlömer <nico.schloemer@gmail.com>
License-Expression: LicenseRef-Proprietary
Project-URL: Homepage, https://github.com/texworld/blacktex
Project-URL: Issues, https://github.com/texworld/blacktex/issues
Keywords: latex
Classifier: Development Status :: 5 - Production/Stable
Classifier: Intended Audience :: Science/Research
Classifier: Operating System :: OS Independent
Classifier: Programming Language :: Python :: 3
Classifier: Programming Language :: Python :: 3.9
Classifier: Programming Language :: Python :: 3.10
Classifier: Programming Language :: Python :: 3.11
Classifier: Programming Language :: Python :: 3.12
Classifier: Topic :: Text Editors :: Text Processing
Classifier: Topic :: Text Processing
Classifier: Topic :: Text Processing :: Markup
Classifier: Topic :: Text Processing :: Markup :: LaTeX
Classifier: Topic :: Utilities
Requires-Python: >=3.9
Requires-Dist: pylatexenc
Requires-Dist: stonefish-license-manager>=0.5.24
Requires-Dist: x22>=0.2.1
